s1300231_learn/__init__.py
s1300231_learn-0.1.0.dist-info/METADATA
s1300231_learn-0.1.0.dist-info/WHEEL
s1300231_learn-0.1.0.dist-info/top_level.txt
s1300231_learn-0.1.0.dist-info/RECORD
